excelmcp/__init__.py
excelmcp-1.0.1.dist-info/METADATA
excelmcp-1.0.1.dist-info/WHEEL
excelmcp-1.0.1.dist-info/entry_points.txt
excelmcp-1.0.1.dist-info/RECORD
