Metadata-Version: 2.4
Name: excelmcp
Version: 1.0.1
Summary: This is a MCP server tool for ai to automate microsoft excel application
Author-email: Monologist <monologist@mail.ustc.edu.cn>
Requires-Python: >=3.11.4
Requires-Dist: fastmcp>=2.3.0
Requires-Dist: openpyxl>=3.1.5
Requires-Dist: pywin32>=310
